CHANGELOG.txt
MANIFEST.in
README.md
setup.py
diskwel/__init__.py
diskwel/generator.py
diskwel/generatorWelc.py
diskwel/assets/card.png
diskwel/assets/dnd.png
diskwel/assets/font.ttf
diskwel/assets/font2.ttf
diskwel/assets/idle.png
diskwel/assets/offline.png
diskwel/assets/online.png
diskwel/assets/streaming.png
disrank2.egg-info/PKG-INFO
disrank2.egg-info/SOURCES.txt
disrank2.egg-info/dependency_links.txt
disrank2.egg-info/requires.txt
disrank2.egg-info/top_level.txt
examples/discord.py