Metadata-Version: 2.1
Name: disrank2
Version: 0.0.4
Summary: Simple lib for discord rank card
Home-page: https://github.com/Otartist/disrank2
Author: Otartist
License: MIT
Keywords: discord discord-rank discord-profile discord-leveling
Platform: UNKNOWN
Classifier: Development Status :: 5 - Production/Stable
Classifier: Intended Audience :: Education
Classifier: Operating System :: POSIX :: Linux
Classifier: Operating System :: Microsoft :: Windows
Classifier: Operating System :: MacOS
Classifier: License :: OSI Approved :: MIT License
Classifier: Programming Language :: Python :: 3
